django_ulidx/.DS_Store
django_ulidx/__init__.py
django_ulidx/apps.py
django_ulidx/migrations/__init__.py
django_ulidx/models.py
django_ulidx/tests.py
django_ulidx/views.py
django_ulidx-1.0.10.dist-info/METADATA
django_ulidx-1.0.10.dist-info/WHEEL
django_ulidx-1.0.10.dist-info/RECORD
