Metadata-Version: 2.4
Name: django_ulidx
Version: 1.0.10
Summary: 
License-Expression: MIT
Author: Poetry User
Author-email: pypi.clock071@passinbox.com
Requires-Python: >=3.14
Classifier: Programming Language :: Python :: 3
Classifier: Programming Language :: Python :: 3.14
Requires-Dist: django (>=6.0)
Requires-Dist: python-ulid (>=3.1.0)
